ssh_agent_add_id-0.0.9.dist-info/METADATA
ssh_agent_add_id-0.0.9.dist-info/WHEEL
ssh_agent_add_id-0.0.9.dist-info/entry_points.txt
ssh_agent_add_id-0.0.9.dist-info/licenses/LICENSE.txt
ssh_agent_add_id/__init__.py
ssh_agent_add_id/__main__.py
ssh_agent_add_id/cli.py
ssh_agent_add_id/cli_arguments.py
ssh_agent_add_id/constants.py
ssh_agent_add_id/errors.py
ssh_agent_add_id/signal_handler.py
ssh_agent_add_id/ssh_agent.py
ssh_agent_add_id-0.0.9.dist-info/RECORD
