Metadata-Version: 2.1
Name: ssh-agent-add-id
Version: 0.0.9
Summary: A wrapper for ssh-add that checks whether a key has already been added to the SSH agent rather than prompting for the passphrase every time.
Keywords: ssh,ssh-add,ssh-agent,authentication,key,identity,vscode,vs code,visual studio code,wsl,wsl2,git,github,gitlab,bitbucket
Author: Alexis Bergue
License: MIT License
Classifier: Development Status :: 3 - Alpha
Classifier: License :: OSI Approved :: MIT License
Classifier: Programming Language :: Python :: 3
Classifier: Programming Language :: Python :: 3.8
Classifier: Programming Language :: Python :: 3.9
Classifier: Programming Language :: Python :: 3.10
Classifier: Programming Language :: Python :: 3.11
Classifier: Programming Language :: Python :: 3.12
Classifier: Operating System :: POSIX
Classifier: Topic :: System :: Networking
Project-URL: Homepage, https://github.com/alexisbg/ssh-agent-add-id
Project-URL: Issues, https://github.com/alexisbg/ssh-agent-add-id/issues
Project-URL: Repository, https://github.com/alexisbg/ssh-agent-add-id
Requires-Python: >=3.8
Requires-Dist: pexpect~=4.9
Requires-Dist: pydantic~=2.7
Requires-Dist: coverage~=7.5; extra == "dev"
Requires-Dist: pytest~=8.2; extra == "dev"
Requires-Dist: pytest-mock~=3.14; extra == "dev"
Requires-Dist: ruff~=0.4; extra == "dev"
Provides-Extra: dev
